htmlpack/__init__.py
htmlpack/__main__.py
htmlpack/htmlpack.py
htmlpack-0.1.2.dist-info/METADATA
htmlpack-0.1.2.dist-info/WHEEL
htmlpack-0.1.2.dist-info/licenses/LICENSE
htmlpack-0.1.2.dist-info/RECORD
