Metadata-Version: 2.1
Name: htmlpack
Version: 0.1.2
Summary: Pre-process HTML files for production environments. Strip HTML comments.
Project-URL: Homepage, https://github.com/conormag/htmlpack
Project-URL: Bug Tracker, https://github.com/conormag/htmlpack/issues
Author-email: Conor Maguire <conormag@gmail.com>
License-File: LICENSE
Classifier: License :: OSI Approved :: MIT License
Classifier: Operating System :: OS Independent
Classifier: Programming Language :: Python :: 3
Requires-Python: >=3.7
